[{"batches": [{"train_loss": 0.6325902938842773, "train_batch_size": 32}, {"train_loss": 0.47119224071502686, "train_batch_size": 32}, {"train_loss": 0.3187794089317322, "train_batch_size": 32}, {"train_loss": 0.33791428804397583, "train_batch_size": 32}, {"train_loss": 0.4132615327835083, "train_batch_size": 32}, {"train_loss": 0.2167794555425644, "train_batch_size": 32}, {"train_loss": 0.15390829741954803, "train_batch_size": 32}, {"train_loss": 0.5365402698516846, "train_batch_size": 32}, {"train_loss": 0.4852524697780609, "train_batch_size": 32}, {"train_loss": 0.2788620889186859, "train_batch_size": 32}, {"train_loss": 0.6030395030975342, "train_batch_size": 32}, {"train_loss": 0.2163272202014923, "train_batch_size": 32}, {"train_loss": 0.6696604490280151, "train_batch_size": 32}, {"train_loss": 0.4593924880027771, "train_batch_size": 32}, {"train_loss": 0.2055647075176239, "train_batch_size": 32}, {"train_loss": 0.44639354944229126, "train_batch_size": 32}, {"train_loss": 0.19069698452949524, "train_batch_size": 32}, {"train_loss": 0.23717042803764343, "train_batch_size": 32}, {"train_loss": 0.4702179431915283, "train_batch_size": 32}, {"train_loss": 0.4137718081474304, "train_batch_size": 32}, {"train_loss": 0.19238075613975525, "train_batch_size": 32}, {"train_loss": 0.23563581705093384, "train_batch_size": 32}, {"train_loss": 0.5178166031837463, "train_batch_size": 32}, {"train_loss": 0.2967368960380554, "train_batch_size": 32}, {"train_loss": 0.39449572563171387, "train_batch_size": 32}, {"train_loss": 0.18418580293655396, "train_batch_size": 32}, {"train_loss": 0.6926275491714478, "train_batch_size": 32}, {"train_loss": 0.3712771534919739, "train_batch_size": 32}, {"train_loss": 0.21579499542713165, "train_batch_size": 32}, {"train_loss": 0.3473034203052521, "train_batch_size": 32}, {"train_loss": 0.35357794165611267, "train_batch_size": 32}, {"train_loss": 0.28936073184013367, "train_batch_size": 32}, {"train_loss": 0.21988284587860107, "train_batch_size": 32}, {"train_loss": 0.16124282777309418, "train_batch_size": 32}, {"train_loss": 0.3634503483772278, "train_batch_size": 32}, {"train_loss": 0.34631264209747314, "train_batch_size": 32}, {"train_loss": 0.21918576955795288, "train_batch_size": 32}, {"train_loss": 0.6565805673599243, "train_batch_size": 32}, {"train_loss": 0.36493709683418274, "train_batch_size": 32}, {"train_loss": 0.4252379536628723, "train_batch_size": 32}, {"train_loss": 0.31367045640945435, "train_batch_size": 32}, {"train_loss": 0.5179973840713501, "train_batch_size": 32}, {"train_loss": 0.28796759247779846, "train_batch_size": 32}, {"train_loss": 0.18853279948234558, "train_batch_size": 32}, {"train_loss": 0.2793530821800232, "train_batch_size": 32}, {"train_loss": 0.4949946403503418, "train_batch_size": 32}, {"train_loss": 0.1060444563627243, "train_batch_size": 32}, {"train_loss": 0.338626503944397, "train_batch_size": 32}, {"train_loss": 0.23547105491161346, "train_batch_size": 32}, {"train_loss": 0.3113088011741638, "train_batch_size": 32}, {"train_loss": 0.20665384829044342, "train_batch_size": 32}, {"train_loss": 0.3453054130077362, "train_batch_size": 32}, {"train_loss": 0.3842402398586273, "train_batch_size": 32}, {"train_loss": 0.3031981587409973, "train_batch_size": 32}, {"train_loss": 0.18538519740104675, "train_batch_size": 32}, {"train_loss": 0.33726009726524353, "train_batch_size": 32}, {"train_loss": 0.31449759006500244, "train_batch_size": 32}, {"train_loss": 0.41220736503601074, "train_batch_size": 32}, {"train_loss": 0.24507620930671692, "train_batch_size": 32}, {"train_loss": 0.2796066403388977, "train_batch_size": 32}, {"train_loss": 0.39375579357147217, "train_batch_size": 32}, {"train_loss": 0.4351021349430084, "train_batch_size": 32}, {"train_loss": 0.31048402190208435, "train_batch_size": 32}, {"train_loss": 0.454828143119812, "train_batch_size": 32}, {"train_loss": 0.2063753604888916, "train_batch_size": 32}, {"train_loss": 0.41563498973846436, "train_batch_size": 32}, {"train_loss": 0.3609115481376648, "train_batch_size": 32}, {"train_loss": 0.3741045296192169, "train_batch_size": 32}, {"train_loss": 0.281477153301239, "train_batch_size": 32}, {"train_loss": 0.5064162611961365, "train_batch_size": 32}, {"train_loss": 0.4026672840118408, "train_batch_size": 32}, {"train_loss": 0.333507776260376, "train_batch_size": 32}, {"train_loss": 0.28892695903778076, "train_batch_size": 32}, {"train_loss": 0.3346182107925415, "train_batch_size": 32}, {"train_loss": 0.38074249029159546, "train_batch_size": 32}, {"train_loss": 0.4500439763069153, "train_batch_size": 32}, {"train_loss": 0.30142655968666077, "train_batch_size": 32}, {"train_loss": 0.4661049544811249, "train_batch_size": 32}, {"train_loss": 0.28622573614120483, "train_batch_size": 32}, {"train_loss": 0.12237177789211273, "train_batch_size": 32}, {"train_loss": 0.23311609029769897, "train_batch_size": 32}, {"train_loss": 0.2269119918346405, "train_batch_size": 32}, {"train_loss": 0.31585776805877686, "train_batch_size": 32}, {"train_loss": 0.3290119171142578, "train_batch_size": 32}, {"train_loss": 0.5098479986190796, "train_batch_size": 32}, {"train_loss": 0.3256711959838867, "train_batch_size": 32}, {"train_loss": 0.40501105785369873, "train_batch_size": 32}, {"train_loss": 0.3276841938495636, "train_batch_size": 32}, {"train_loss": 0.18713149428367615, "train_batch_size": 32}, {"train_loss": 0.49636781215667725, "train_batch_size": 32}, {"train_loss": 0.29582124948501587, "train_batch_size": 32}, {"train_loss": 0.3705751895904541, "train_batch_size": 32}, {"train_loss": 0.3274461030960083, "train_batch_size": 32}, {"train_loss": 0.3929882049560547, "train_batch_size": 32}, {"train_loss": 0.17690971493721008, "train_batch_size": 32}, {"train_loss": 0.1457153856754303, "train_batch_size": 32}, {"train_loss": 0.28591933846473694, "train_batch_size": 32}, {"train_loss": 0.5580821633338928, "train_batch_size": 32}, {"train_loss": 0.5292994976043701, "train_batch_size": 32}, {"train_loss": 0.40168753266334534, "train_batch_size": 32}, {"train_loss": 0.22309479117393494, "train_batch_size": 32}, {"train_loss": 0.09058094769716263, "train_batch_size": 32}, {"train_loss": 0.20665115118026733, "train_batch_size": 32}, {"train_loss": 0.2366567850112915, "train_batch_size": 32}, {"train_loss": 0.21488092839717865, "train_batch_size": 32}, {"train_loss": 0.6856529116630554, "train_batch_size": 32}, {"train_loss": 0.3543357849121094, "train_batch_size": 32}, {"train_loss": 0.4494689702987671, "train_batch_size": 32}, {"train_loss": 0.28390246629714966, "train_batch_size": 32}, {"train_loss": 0.4593285322189331, "train_batch_size": 32}, {"train_loss": 0.45715469121932983, "train_batch_size": 32}, {"train_loss": 0.2855777442455292, "train_batch_size": 32}, {"train_loss": 0.25360819697380066, "train_batch_size": 32}, {"train_loss": 0.24524587392807007, "train_batch_size": 32}, {"train_loss": 0.29543817043304443, "train_batch_size": 32}, {"train_loss": 0.343066930770874, "train_batch_size": 32}, {"train_loss": 0.18828074634075165, "train_batch_size": 32}, {"train_loss": 0.2941998541355133, "train_batch_size": 32}, {"train_loss": 0.2468518167734146, "train_batch_size": 32}, {"train_loss": 0.17096662521362305, "train_batch_size": 32}, {"train_loss": 0.3135085701942444, "train_batch_size": 32}, {"train_loss": 0.38943353295326233, "train_batch_size": 32}, {"train_loss": 0.43825262784957886, "train_batch_size": 32}, {"train_loss": 0.16612622141838074, "train_batch_size": 32}, {"train_loss": 0.1455751657485962, "train_batch_size": 32}, {"train_loss": 0.23425835371017456, "train_batch_size": 32}, {"train_loss": 0.5211273431777954, "train_batch_size": 32}, {"train_loss": 0.3345632255077362, "train_batch_size": 32}, {"train_loss": 0.31040942668914795, "train_batch_size": 32}, {"train_loss": 0.3867257535457611, "train_batch_size": 32}, {"train_loss": 0.16958346962928772, "train_batch_size": 32}, {"train_loss": 0.4681340754032135, "train_batch_size": 32}, {"train_loss": 0.09784851223230362, "train_batch_size": 32}, {"train_loss": 0.15197038650512695, "train_batch_size": 32}, {"train_loss": 0.3403778374195099, "train_batch_size": 32}, {"train_loss": 0.19039863348007202, "train_batch_size": 32}, {"train_loss": 0.41248905658721924, "train_batch_size": 32}, {"train_loss": 0.25505951046943665, "train_batch_size": 32}, {"train_loss": 0.2633466124534607, "train_batch_size": 32}, {"train_loss": 0.47044527530670166, "train_batch_size": 32}, {"train_loss": 0.3572692275047302, "train_batch_size": 32}, {"train_loss": 0.4058651924133301, "train_batch_size": 32}, {"train_loss": 0.23824605345726013, "train_batch_size": 32}, {"train_loss": 0.10787667334079742, "train_batch_size": 32}, {"train_loss": 0.24952635169029236, "train_batch_size": 32}, {"train_loss": 0.2418326437473297, "train_batch_size": 32}, {"train_loss": 0.28817981481552124, "train_batch_size": 32}, {"train_loss": 0.33044177293777466, "train_batch_size": 32}, {"train_loss": 0.3304823637008667, "train_batch_size": 32}, {"train_loss": 0.24362406134605408, "train_batch_size": 32}, {"train_loss": 0.1919078379869461, "train_batch_size": 32}, {"train_loss": 0.25280874967575073, "train_batch_size": 32}, {"train_loss": 0.17698080837726593, "train_batch_size": 32}, {"train_loss": 0.17361891269683838, "train_batch_size": 32}, {"train_loss": 0.22274838387966156, "train_batch_size": 32}, {"train_loss": 0.22652015089988708, "train_batch_size": 32}, {"train_loss": 0.20286661386489868, "train_batch_size": 32}, {"train_loss": 0.5286002159118652, "train_batch_size": 32}, {"train_loss": 0.4618260860443115, "train_batch_size": 32}, {"train_loss": 0.3780852258205414, "train_batch_size": 32}, {"train_loss": 0.2568231225013733, "train_batch_size": 32}, {"train_loss": 0.34286370873451233, "train_batch_size": 32}, {"train_loss": 0.16311395168304443, "train_batch_size": 32}, {"train_loss": 0.18385112285614014, "train_batch_size": 32}, {"train_loss": 0.4691826105117798, "train_batch_size": 32}, {"train_loss": 0.249485582113266, "train_batch_size": 32}, {"train_loss": 0.29598551988601685, "train_batch_size": 32}, {"train_loss": 0.2950950264930725, "train_batch_size": 32}, {"train_loss": 0.7831093072891235, "train_batch_size": 32}, {"train_loss": 0.23963958024978638, "train_batch_size": 32}, {"train_loss": 0.43124574422836304, "train_batch_size": 32}, {"train_loss": 0.31638798117637634, "train_batch_size": 32}, {"train_loss": 0.2136368304491043, "train_batch_size": 32}, {"train_loss": 0.30014610290527344, "train_batch_size": 32}, {"train_loss": 0.3738887310028076, "train_batch_size": 32}, {"train_loss": 0.29301717877388, "train_batch_size": 32}, {"train_loss": 0.338295042514801, "train_batch_size": 32}, {"train_loss": 0.3151853084564209, "train_batch_size": 32}, {"train_loss": 0.5062511563301086, "train_batch_size": 32}, {"train_loss": 0.3028315007686615, "train_batch_size": 32}, {"train_loss": 0.3120604157447815, "train_batch_size": 32}, {"train_loss": 0.20960074663162231, "train_batch_size": 32}, {"train_loss": 0.2892929017543793, "train_batch_size": 32}, {"train_loss": 0.23164193332195282, "train_batch_size": 32}, {"train_loss": 0.17998552322387695, "train_batch_size": 32}, {"train_loss": 0.26962539553642273, "train_batch_size": 32}, {"train_loss": 0.34364035725593567, "train_batch_size": 32}, {"train_loss": 0.32921746373176575, "train_batch_size": 32}, {"train_loss": 0.2836109399795532, "train_batch_size": 32}, {"train_loss": 0.47932738065719604, "train_batch_size": 32}, {"train_loss": 0.2942614257335663, "train_batch_size": 32}, {"train_loss": 0.4913928806781769, "train_batch_size": 32}, {"train_loss": 0.32472994923591614, "train_batch_size": 32}, {"train_loss": 0.41450923681259155, "train_batch_size": 32}, {"train_loss": 0.25610795617103577, "train_batch_size": 32}, {"train_loss": 0.19640950858592987, "train_batch_size": 32}, {"train_loss": 0.4214843511581421, "train_batch_size": 32}, {"train_loss": 0.3480832278728485, "train_batch_size": 32}, {"train_loss": 0.5510745048522949, "train_batch_size": 32}, {"train_loss": 0.376003235578537, "train_batch_size": 32}, {"train_loss": 0.3789915144443512, "train_batch_size": 32}, {"train_loss": 0.4165535569190979, "train_batch_size": 32}, {"train_loss": 0.3007161319255829, "train_batch_size": 32}, {"train_loss": 0.4577177166938782, "train_batch_size": 32}, {"train_loss": 0.320081889629364, "train_batch_size": 32}, {"train_loss": 0.3525216281414032, "train_batch_size": 32}, {"train_loss": 0.1996764987707138, "train_batch_size": 32}, {"train_loss": 0.25235268473625183, "train_batch_size": 32}, {"train_loss": 0.2025163173675537, "train_batch_size": 32}, {"train_loss": 0.2840256094932556, "train_batch_size": 32}, {"train_loss": 0.2788347005844116, "train_batch_size": 32}, {"train_loss": 0.11449825018644333, "train_batch_size": 32}, {"train_loss": 0.2860366404056549, "train_batch_size": 32}, {"train_loss": 0.44532865285873413, "train_batch_size": 32}, {"train_loss": 0.27507084608078003, "train_batch_size": 32}, {"train_loss": 0.15402095019817352, "train_batch_size": 32}, {"train_loss": 0.43499448895454407, "train_batch_size": 32}, {"train_loss": 0.3268105387687683, "train_batch_size": 32}, {"train_loss": 0.1598391830921173, "train_batch_size": 32}, {"train_loss": 0.33243003487586975, "train_batch_size": 32}, {"train_loss": 0.14017391204833984, "train_batch_size": 32}, {"train_loss": 0.2939116060733795, "train_batch_size": 32}, {"train_loss": 0.21661530435085297, "train_batch_size": 32}, {"train_loss": 0.5104703903198242, "train_batch_size": 32}, {"train_loss": 0.3330082297325134, "train_batch_size": 32}, {"train_loss": 0.5286579728126526, "train_batch_size": 32}, {"train_loss": 0.14445002377033234, "train_batch_size": 32}, {"train_loss": 0.10474023222923279, "train_batch_size": 32}, {"train_loss": 0.22322672605514526, "train_batch_size": 32}, {"train_loss": 0.2544446587562561, "train_batch_size": 32}, {"train_loss": 0.3416886031627655, "train_batch_size": 32}, {"train_loss": 0.29667556285858154, "train_batch_size": 32}, {"train_loss": 0.311038613319397, "train_batch_size": 32}, {"train_loss": 0.5134928822517395, "train_batch_size": 32}, {"train_loss": 0.18896225094795227, "train_batch_size": 32}, {"train_loss": 0.23011593520641327, "train_batch_size": 32}, {"train_loss": 0.44976234436035156, "train_batch_size": 32}, {"train_loss": 0.21307089924812317, "train_batch_size": 32}, {"train_loss": 0.403592586517334, "train_batch_size": 32}, {"train_loss": 0.21197275817394257, "train_batch_size": 32}, {"train_loss": 0.18738512694835663, "train_batch_size": 32}, {"train_loss": 0.2701389789581299, "train_batch_size": 32}, {"train_loss": 0.26304173469543457, "train_batch_size": 32}, {"train_loss": 0.4521176218986511, "train_batch_size": 32}, {"train_loss": 0.29866617918014526, "train_batch_size": 32}, {"train_loss": 0.3142309784889221, "train_batch_size": 32}, {"train_loss": 0.5195401310920715, "train_batch_size": 32}, {"train_loss": 0.3661198019981384, "train_batch_size": 32}, {"train_loss": 0.4466751217842102, "train_batch_size": 32}, {"train_loss": 0.43283408880233765, "train_batch_size": 32}, {"train_loss": 0.2624768018722534, "train_batch_size": 32}, {"train_loss": 0.3517912030220032, "train_batch_size": 32}, {"train_loss": 0.26003995537757874, "train_batch_size": 32}, {"train_loss": 0.41074782609939575, "train_batch_size": 32}, {"train_loss": 0.4426150321960449, "train_batch_size": 32}, {"train_loss": 0.23548147082328796, "train_batch_size": 32}, {"train_loss": 0.29919376969337463, "train_batch_size": 32}, {"train_loss": 0.1734112799167633, "train_batch_size": 32}, {"train_loss": 0.21522939205169678, "train_batch_size": 32}, {"train_loss": 0.40222376585006714, "train_batch_size": 32}, {"train_loss": 0.41433343291282654, "train_batch_size": 32}, {"train_loss": 0.41284888982772827, "train_batch_size": 32}, {"train_loss": 0.3395369350910187, "train_batch_size": 32}, {"train_loss": 0.22491022944450378, "train_batch_size": 32}, {"train_loss": 0.28967493772506714, "train_batch_size": 32}, {"train_loss": 0.265900194644928, "train_batch_size": 32}, {"train_loss": 0.20047524571418762, "train_batch_size": 32}, {"train_loss": 0.43395131826400757, "train_batch_size": 32}, {"train_loss": 0.2730216979980469, "train_batch_size": 32}, {"train_loss": 0.47890812158584595, "train_batch_size": 32}, {"train_loss": 0.20710694789886475, "train_batch_size": 32}, {"train_loss": 0.28171855211257935, "train_batch_size": 32}, {"train_loss": 0.2940857410430908, "train_batch_size": 32}, {"train_loss": 0.3360491096973419, "train_batch_size": 32}, {"train_loss": 0.19895824790000916, "train_batch_size": 32}, {"train_loss": 0.3214532732963562, "train_batch_size": 32}, {"train_loss": 0.4914636015892029, "train_batch_size": 32}, {"train_loss": 0.48423585295677185, "train_batch_size": 32}, {"train_loss": 0.3233579397201538, "train_batch_size": 32}, {"train_loss": 0.22144058346748352, "train_batch_size": 32}, {"train_loss": 0.3539002239704132, "train_batch_size": 32}, {"train_loss": 0.1873195767402649, "train_batch_size": 32}, {"train_loss": 0.16232076287269592, "train_batch_size": 32}, {"train_loss": 0.322631299495697, "train_batch_size": 32}, {"train_loss": 0.29877737164497375, "train_batch_size": 32}, {"train_loss": 0.36770063638687134, "train_batch_size": 32}, {"train_loss": 0.2631426751613617, "train_batch_size": 32}, {"train_loss": 0.31185469031333923, "train_batch_size": 32}, {"train_loss": 0.3807190954685211, "train_batch_size": 32}, {"train_loss": 0.3116772174835205, "train_batch_size": 32}, {"train_loss": 0.2727400064468384, "train_batch_size": 32}, {"train_loss": 0.3295285999774933, "train_batch_size": 32}, {"train_loss": 0.35005173087120056, "train_batch_size": 32}, {"train_loss": 0.19044211506843567, "train_batch_size": 32}, {"train_loss": 0.13606449961662292, "train_batch_size": 32}, {"train_loss": 0.4440969228744507, "train_batch_size": 32}, {"train_loss": 0.10913673788309097, "train_batch_size": 32}, {"train_loss": 0.32390525937080383, "train_batch_size": 32}, {"train_loss": 0.36797475814819336, "train_batch_size": 32}, {"train_loss": 0.4848681092262268, "train_batch_size": 32}, {"train_loss": 0.3466743230819702, "train_batch_size": 32}, {"train_loss": 0.36971014738082886, "train_batch_size": 32}, {"train_loss": 0.32590219378471375, "train_batch_size": 32}, {"train_loss": 0.39771559834480286, "train_batch_size": 32}, {"train_loss": 0.3693508207798004, "train_batch_size": 32}, {"train_loss": 0.49356383085250854, "train_batch_size": 32}, {"train_loss": 0.21338042616844177, "train_batch_size": 32}, {"train_loss": 0.32252055406570435, "train_batch_size": 32}, {"train_loss": 0.3425433039665222, "train_batch_size": 32}, {"train_loss": 0.2183239459991455, "train_batch_size": 32}, {"train_loss": 0.5517240762710571, "train_batch_size": 32}, {"train_loss": 0.28451985120773315, "train_batch_size": 32}, {"train_loss": 0.16132308542728424, "train_batch_size": 32}, {"train_loss": 0.2817763090133667, "train_batch_size": 32}, {"train_loss": 0.2884247303009033, "train_batch_size": 32}, {"train_loss": 0.5286998748779297, "train_batch_size": 32}, {"train_loss": 0.34889620542526245, "train_batch_size": 32}, {"train_loss": 0.19493639469146729, "train_batch_size": 32}, {"train_loss": 0.21664826571941376, "train_batch_size": 32}, {"train_loss": 0.21028487384319305, "train_batch_size": 32}, {"train_loss": 0.12716561555862427, "train_batch_size": 32}, {"train_loss": 0.7333887219429016, "train_batch_size": 32}, {"train_loss": 0.33767804503440857, "train_batch_size": 32}, {"train_loss": 0.11764197796583176, "train_batch_size": 32}, {"train_loss": 0.09749016165733337, "train_batch_size": 32}, {"train_loss": 0.34283316135406494, "train_batch_size": 32}, {"train_loss": 0.37858906388282776, "train_batch_size": 32}, {"train_loss": 0.4305758476257324, "train_batch_size": 32}, {"train_loss": 0.40099233388900757, "train_batch_size": 32}, {"train_loss": 0.12685489654541016, "train_batch_size": 32}, {"train_loss": 0.22267520427703857, "train_batch_size": 32}, {"train_loss": 0.44762295484542847, "train_batch_size": 32}, {"train_loss": 0.2703714668750763, "train_batch_size": 32}, {"train_loss": 0.26060962677001953, "train_batch_size": 32}, {"train_loss": 0.11818696558475494, "train_batch_size": 32}, {"train_loss": 0.23407495021820068, "train_batch_size": 32}, {"train_loss": 0.355873167514801, "train_batch_size": 32}, {"train_loss": 0.1993342638015747, "train_batch_size": 32}, {"train_loss": 0.24208292365074158, "train_batch_size": 32}, {"train_loss": 0.1107625737786293, "train_batch_size": 32}, {"train_loss": 0.3188112676143646, "train_batch_size": 32}, {"train_loss": 0.29350337386131287, "train_batch_size": 32}, {"train_loss": 0.19186733663082123, "train_batch_size": 32}, {"train_loss": 0.16489751636981964, "train_batch_size": 32}, {"train_loss": 0.34150123596191406, "train_batch_size": 32}, {"train_loss": 0.2986867427825928, "train_batch_size": 32}, {"train_loss": 0.3201877772808075, "train_batch_size": 32}, {"train_loss": 0.27857792377471924, "train_batch_size": 32}, {"train_loss": 0.36861181259155273, "train_batch_size": 32}, {"train_loss": 0.44714558124542236, "train_batch_size": 32}, {"train_loss": 0.4189639985561371, "train_batch_size": 32}, {"train_loss": 0.3737407326698303, "train_batch_size": 32}, {"train_loss": 0.3693399131298065, "train_batch_size": 32}, {"train_loss": 0.3755214214324951, "train_batch_size": 32}, {"train_loss": 0.26835423707962036, "train_batch_size": 32}, {"train_loss": 0.1444334089756012, "train_batch_size": 32}, {"train_loss": 0.20556242763996124, "train_batch_size": 32}, {"train_loss": 0.41448283195495605, "train_batch_size": 32}, {"train_loss": 0.09277953952550888, "train_batch_size": 32}, {"train_loss": 0.14669378101825714, "train_batch_size": 32}, {"train_loss": 0.08273786306381226, "train_batch_size": 32}, {"train_loss": 0.47733160853385925, "train_batch_size": 32}, {"train_loss": 0.34965986013412476, "train_batch_size": 32}, {"train_loss": 0.18031345307826996, "train_batch_size": 32}, {"train_loss": 0.4626651108264923, "train_batch_size": 32}, {"train_loss": 0.2992614507675171, "train_batch_size": 32}, {"train_loss": 0.36089009046554565, "train_batch_size": 32}, {"train_loss": 0.3065049350261688, "train_batch_size": 32}, {"train_loss": 0.2046755850315094, "train_batch_size": 32}, {"train_loss": 0.3167080581188202, "train_batch_size": 32}, {"train_loss": 0.2738751173019409, "train_batch_size": 32}, {"train_loss": 0.38113853335380554, "train_batch_size": 32}, {"train_loss": 0.36422351002693176, "train_batch_size": 32}, {"train_loss": 0.40816545486450195, "train_batch_size": 32}, {"train_loss": 0.23202218115329742, "train_batch_size": 32}, {"train_loss": 0.3399884104728699, "train_batch_size": 32}, {"train_loss": 0.25564855337142944, "train_batch_size": 32}, {"train_loss": 0.36476004123687744, "train_batch_size": 32}, {"train_loss": 0.3516302704811096, "train_batch_size": 32}, {"train_loss": 0.28714272379875183, "train_batch_size": 32}, {"train_loss": 0.32015424966812134, "train_batch_size": 32}, {"train_loss": 0.2952839732170105, "train_batch_size": 32}, {"train_loss": 0.29377150535583496, "train_batch_size": 32}, {"train_loss": 0.4044033885002136, "train_batch_size": 32}, {"train_loss": 0.3604680299758911, "train_batch_size": 32}, {"train_loss": 0.2573797106742859, "train_batch_size": 32}, {"train_loss": 0.17869073152542114, "train_batch_size": 32}, {"train_loss": 0.19863279163837433, "train_batch_size": 32}, {"train_loss": 0.19952522218227386, "train_batch_size": 32}, {"train_loss": 0.36773067712783813, "train_batch_size": 32}, {"train_loss": 0.35036569833755493, "train_batch_size": 32}, {"train_loss": 0.38603371381759644, "train_batch_size": 32}, {"train_loss": 0.18075987696647644, "train_batch_size": 32}, {"train_loss": 0.187718465924263, "train_batch_size": 32}, {"train_loss": 0.20740948617458344, "train_batch_size": 32}, {"train_loss": 0.34664058685302734, "train_batch_size": 32}, {"train_loss": 0.41884922981262207, "train_batch_size": 32}, {"train_loss": 0.14456142485141754, "train_batch_size": 32}, {"train_loss": 0.23169104754924774, "train_batch_size": 32}, {"train_loss": 0.3897453546524048, "train_batch_size": 32}, {"train_loss": 0.2044525146484375, "train_batch_size": 32}, {"train_loss": 0.44773536920547485, "train_batch_size": 32}, {"train_loss": 0.27651238441467285, "train_batch_size": 32}, {"train_loss": 0.2981978952884674, "train_batch_size": 32}, {"train_loss": 0.24144025146961212, "train_batch_size": 32}, {"train_loss": 0.30112096667289734, "train_batch_size": 32}, {"train_loss": 0.35174310207366943, "train_batch_size": 32}, {"train_loss": 0.26232367753982544, "train_batch_size": 32}, {"train_loss": 0.36063724756240845, "train_batch_size": 32}, {"train_loss": 0.3160942792892456, "train_batch_size": 32}, {"train_loss": 0.2957632541656494, "train_batch_size": 32}, {"train_loss": 0.576356053352356, "train_batch_size": 32}, {"train_loss": 0.27379879355430603, "train_batch_size": 32}, {"train_loss": 0.26477915048599243, "train_batch_size": 32}, {"train_loss": 0.28902846574783325, "train_batch_size": 32}, {"train_loss": 0.2695141136646271, "train_batch_size": 32}, {"train_loss": 0.14916159212589264, "train_batch_size": 32}, {"train_loss": 0.30179333686828613, "train_batch_size": 32}, {"train_loss": 0.32756417989730835, "train_batch_size": 32}, {"train_loss": 0.16560238599777222, "train_batch_size": 32}, {"train_loss": 0.22209379076957703, "train_batch_size": 32}, {"train_loss": 0.4250994920730591, "train_batch_size": 32}, {"train_loss": 0.3013780117034912, "train_batch_size": 32}, {"train_loss": 0.3054163157939911, "train_batch_size": 32}, {"train_loss": 0.28974097967147827, "train_batch_size": 32}, {"train_loss": 0.15082941949367523, "train_batch_size": 32}, {"train_loss": 0.250862181186676, "train_batch_size": 32}, {"train_loss": 0.3915141224861145, "train_batch_size": 32}, {"train_loss": 0.22801370918750763, "train_batch_size": 32}, {"train_loss": 0.4269696772098541, "train_batch_size": 32}, {"train_loss": 0.2048405110836029, "train_batch_size": 32}, {"train_loss": 0.21286463737487793, "train_batch_size": 32}, {"train_loss": 0.10925225913524628, "train_batch_size": 32}, {"train_loss": 0.22631452977657318, "train_batch_size": 32}, {"train_loss": 0.23622527718544006, "train_batch_size": 32}, {"train_loss": 0.36996176838874817, "train_batch_size": 32}, {"train_loss": 0.48019325733184814, "train_batch_size": 32}, {"train_loss": 0.2181772142648697, "train_batch_size": 32}, {"train_loss": 0.14911392331123352, "train_batch_size": 32}, {"train_loss": 0.24273209273815155, "train_batch_size": 32}, {"train_loss": 0.3637845516204834, "train_batch_size": 32}, {"train_loss": 0.21281397342681885, "train_batch_size": 32}, {"train_loss": 0.1918073296546936, "train_batch_size": 32}, {"train_loss": 0.3519309163093567, "train_batch_size": 32}, {"train_loss": 0.26002806425094604, "train_batch_size": 32}, {"train_loss": 0.2452062964439392, "train_batch_size": 32}, {"train_loss": 0.43867212533950806, "train_batch_size": 32}, {"train_loss": 0.22864565253257751, "train_batch_size": 32}, {"train_loss": 0.22730320692062378, "train_batch_size": 32}, {"train_loss": 0.24669033288955688, "train_batch_size": 32}, {"train_loss": 0.40611952543258667, "train_batch_size": 32}, {"train_loss": 0.3562459349632263, "train_batch_size": 32}, {"train_loss": 0.37750256061553955, "train_batch_size": 32}, {"train_loss": 0.3987559676170349, "train_batch_size": 32}, {"train_loss": 0.282086044549942, "train_batch_size": 32}, {"train_loss": 0.23010489344596863, "train_batch_size": 32}, {"train_loss": 0.23234349489212036, "train_batch_size": 32}, {"train_loss": 0.18782076239585876, "train_batch_size": 32}, {"train_loss": 0.09003104269504547, "train_batch_size": 32}, {"train_loss": 0.27707239985466003, "train_batch_size": 32}, {"train_loss": 0.17220041155815125, "train_batch_size": 32}, {"train_loss": 0.37137317657470703, "train_batch_size": 32}, {"train_loss": 0.24326570332050323, "train_batch_size": 32}, {"train_loss": 0.5038444995880127, "train_batch_size": 32}, {"train_loss": 0.21819695830345154, "train_batch_size": 32}, {"train_loss": 0.16637389361858368, "train_batch_size": 32}, {"train_loss": 0.16565418243408203, "train_batch_size": 32}, {"train_loss": 0.4348735213279724, "train_batch_size": 32}, {"train_loss": 0.34773391485214233, "train_batch_size": 32}, {"train_loss": 0.32732850313186646, "train_batch_size": 32}, {"train_loss": 0.31218552589416504, "train_batch_size": 32}, {"train_loss": 0.21059411764144897, "train_batch_size": 32}, {"train_loss": 0.21803799271583557, "train_batch_size": 32}, {"train_loss": 0.29262638092041016, "train_batch_size": 32}, {"train_loss": 0.3406669497489929, "train_batch_size": 32}, {"train_loss": 0.3763149380683899, "train_batch_size": 32}, {"train_loss": 0.14559578895568848, "train_batch_size": 32}, {"train_loss": 0.2681083083152771, "train_batch_size": 32}, {"train_loss": 0.10869109630584717, "train_batch_size": 32}, {"train_loss": 0.3051326870918274, "train_batch_size": 32}, {"train_loss": 0.7274969220161438, "train_batch_size": 32}, {"train_loss": 0.3004056513309479, "train_batch_size": 32}, {"train_loss": 0.3956896662712097, "train_batch_size": 32}, {"train_loss": 0.29104214906692505, "train_batch_size": 32}, {"train_loss": 0.21254862844944, "train_batch_size": 32}, {"train_loss": 0.2749401926994324, "train_batch_size": 32}, {"train_loss": 0.4035804569721222, "train_batch_size": 32}, {"train_loss": 0.48718512058258057, "train_batch_size": 32}, {"train_loss": 0.22057700157165527, "train_batch_size": 32}, {"train_loss": 0.2411649078130722, "train_batch_size": 32}, {"train_loss": 0.4676232635974884, "train_batch_size": 32}, {"train_loss": 0.30223846435546875, "train_batch_size": 32}, {"train_loss": 0.2026897370815277, "train_batch_size": 32}, {"train_loss": 0.5938419103622437, "train_batch_size": 32}, {"train_loss": 0.3691994249820709, "train_batch_size": 32}, {"train_loss": 0.3836383819580078, "train_batch_size": 32}, {"train_loss": 0.5703175663948059, "train_batch_size": 32}, {"train_loss": 0.27904850244522095, "train_batch_size": 32}, {"train_loss": 0.38237449526786804, "train_batch_size": 32}, {"train_loss": 0.3170420229434967, "train_batch_size": 32}, {"train_loss": 0.3364008665084839, "train_batch_size": 32}, {"train_loss": 0.35425418615341187, "train_batch_size": 32}, {"train_loss": 0.24390769004821777, "train_batch_size": 32}, {"train_loss": 0.40224575996398926, "train_batch_size": 32}, {"train_loss": 0.3462963104248047, "train_batch_size": 32}, {"train_loss": 0.27929309010505676, "train_batch_size": 32}, {"train_loss": 0.31996721029281616, "train_batch_size": 32}, {"train_loss": 0.3231399953365326, "train_batch_size": 32}, {"train_loss": 0.33071714639663696, "train_batch_size": 32}, {"train_loss": 0.27818208932876587, "train_batch_size": 32}, {"train_loss": 0.2814320921897888, "train_batch_size": 32}, {"train_loss": 0.3282206058502197, "train_batch_size": 32}, {"train_loss": 0.4688970744609833, "train_batch_size": 32}, {"train_loss": 0.3773564398288727, "train_batch_size": 32}, {"train_loss": 0.29488372802734375, "train_batch_size": 32}, {"train_loss": 0.5689611434936523, "train_batch_size": 32}, {"train_loss": 0.2744585871696472, "train_batch_size": 32}, {"train_loss": 0.23232382535934448, "train_batch_size": 32}, {"train_loss": 0.36499789357185364, "train_batch_size": 32}, {"train_loss": 0.4684672951698303, "train_batch_size": 32}, {"train_loss": 0.25212806463241577, "train_batch_size": 32}, {"train_loss": 0.3485162556171417, "train_batch_size": 32}, {"train_loss": 0.22069226205348969, "train_batch_size": 32}, {"train_loss": 0.23809266090393066, "train_batch_size": 32}, {"train_loss": 0.14495034515857697, "train_batch_size": 32}, {"train_loss": 0.3718225061893463, "train_batch_size": 32}, {"train_loss": 0.33083561062812805, "train_batch_size": 32}, {"train_loss": 0.3065907955169678, "train_batch_size": 32}, {"train_loss": 0.3163541555404663, "train_batch_size": 32}, {"train_loss": 0.3196257948875427, "train_batch_size": 32}, {"train_loss": 0.4356250762939453, "train_batch_size": 32}, {"train_loss": 0.22242578864097595, "train_batch_size": 32}, {"train_loss": 0.16205239295959473, "train_batch_size": 32}, {"train_loss": 0.1976504772901535, "train_batch_size": 32}, {"train_loss": 0.42497989535331726, "train_batch_size": 32}, {"train_loss": 0.3013366758823395, "train_batch_size": 32}, {"train_loss": 0.3230594992637634, "train_batch_size": 32}, {"train_loss": 0.32800179719924927, "train_batch_size": 32}, {"train_loss": 0.1229814887046814, "train_batch_size": 32}, {"train_loss": 0.3364240527153015, "train_batch_size": 32}, {"train_loss": 0.33548930287361145, "train_batch_size": 32}, {"train_loss": 0.23680338263511658, "train_batch_size": 32}, {"train_loss": 0.4008624255657196, "train_batch_size": 32}, {"train_loss": 0.38734033703804016, "train_batch_size": 32}, {"train_loss": 0.24393656849861145, "train_batch_size": 32}, {"train_loss": 0.18895477056503296, "train_batch_size": 32}, {"train_loss": 0.5293530225753784, "train_batch_size": 32}, {"train_loss": 0.20051774382591248, "train_batch_size": 32}, {"train_loss": 0.29023313522338867, "train_batch_size": 32}, {"train_loss": 0.3269006907939911, "train_batch_size": 32}, {"train_loss": 0.2695857286453247, "train_batch_size": 32}, {"train_loss": 0.2694763243198395, "train_batch_size": 32}, {"train_loss": 0.22664326429367065, "train_batch_size": 32}, {"train_loss": 0.34181642532348633, "train_batch_size": 32}, {"train_loss": 0.10642770677804947, "train_batch_size": 32}, {"train_loss": 0.18295761942863464, "train_batch_size": 32}, {"train_loss": 0.2838743329048157, "train_batch_size": 32}, {"train_loss": 0.18671715259552002, "train_batch_size": 32}, {"train_loss": 0.35217684507369995, "train_batch_size": 32}, {"train_loss": 0.21635062992572784, "train_batch_size": 32}, {"train_loss": 0.3400108814239502, "train_batch_size": 32}, {"train_loss": 0.2978864014148712, "train_batch_size": 32}, {"train_loss": 0.25384634733200073, "train_batch_size": 32}, {"train_loss": 0.342143714427948, "train_batch_size": 32}, {"train_loss": 0.5778263807296753, "train_batch_size": 32}, {"train_loss": 0.22392240166664124, "train_batch_size": 32}, {"train_loss": 0.37339240312576294, "train_batch_size": 32}, {"train_loss": 0.14699313044548035, "train_batch_size": 32}, {"train_loss": 0.306861937046051, "train_batch_size": 32}, {"train_loss": 0.5522074699401855, "train_batch_size": 32}, {"train_loss": 0.271670937538147, "train_batch_size": 32}, {"train_loss": 0.15700723230838776, "train_batch_size": 32}, {"train_loss": 0.35369962453842163, "train_batch_size": 32}, {"train_loss": 0.49720877408981323, "train_batch_size": 32}, {"train_loss": 0.2620668411254883, "train_batch_size": 32}, {"train_loss": 0.25840064883232117, "train_batch_size": 32}, {"train_loss": 0.19735275208950043, "train_batch_size": 32}, {"train_loss": 0.3398568034172058, "train_batch_size": 32}, {"train_loss": 0.2573235034942627, "train_batch_size": 32}, {"train_loss": 0.21715033054351807, "train_batch_size": 32}, {"train_loss": 0.22290652990341187, "train_batch_size": 32}, {"train_loss": 0.4833611249923706, "train_batch_size": 32}, {"train_loss": 0.5157266855239868, "train_batch_size": 32}, {"train_loss": 0.41603004932403564, "train_batch_size": 32}, {"train_loss": 0.404333233833313, "train_batch_size": 32}, {"train_loss": 0.29277390241622925, "train_batch_size": 32}, {"train_loss": 0.28199708461761475, "train_batch_size": 32}, {"train_loss": 0.19924293458461761, "train_batch_size": 32}, {"train_loss": 0.35464972257614136, "train_batch_size": 32}, {"train_loss": 0.2330184429883957, "train_batch_size": 32}, {"train_loss": 0.14774641394615173, "train_batch_size": 32}, {"train_loss": 0.22012296319007874, "train_batch_size": 32}, {"train_loss": 0.39585480093955994, "train_batch_size": 32}, {"train_loss": 0.34289443492889404, "train_batch_size": 32}, {"train_loss": 0.12504835426807404, "train_batch_size": 32}, {"train_loss": 0.5100956559181213, "train_batch_size": 32}, {"train_loss": 0.13489022850990295, "train_batch_size": 32}, {"train_loss": 0.44447487592697144, "train_batch_size": 32}, {"train_loss": 0.31394290924072266, "train_batch_size": 32}, {"train_loss": 0.37382638454437256, "train_batch_size": 32}, {"train_loss": 0.41057488322257996, "train_batch_size": 32}, {"train_loss": 0.3758552372455597, "train_batch_size": 32}, {"train_loss": 0.4061385989189148, "train_batch_size": 32}, {"train_loss": 0.36642181873321533, "train_batch_size": 32}, {"train_loss": 0.22438473999500275, "train_batch_size": 32}, {"train_loss": 0.5316623449325562, "train_batch_size": 32}, {"train_loss": 0.22991661727428436, "train_batch_size": 32}, {"train_loss": 0.21575942635536194, "train_batch_size": 32}, {"train_loss": 0.27984172105789185, "train_batch_size": 32}, {"train_loss": 0.1806032657623291, "train_batch_size": 32}, {"train_loss": 0.29192405939102173, "train_batch_size": 32}, {"train_loss": 0.5741851329803467, "train_batch_size": 32}, {"train_loss": 0.30208760499954224, "train_batch_size": 32}, {"train_loss": 0.10534554719924927, "train_batch_size": 32}, {"train_loss": 0.3708743453025818, "train_batch_size": 32}, {"train_loss": 0.41283655166625977, "train_batch_size": 32}, {"train_loss": 0.46487563848495483, "train_batch_size": 32}, {"train_loss": 0.3831920623779297, "train_batch_size": 32}, {"train_loss": 0.216143399477005, "train_batch_size": 32}, {"train_loss": 0.2889407277107239, "train_batch_size": 32}, {"train_loss": 0.5273224711418152, "train_batch_size": 32}, {"train_loss": 0.19234636425971985, "train_batch_size": 32}, {"train_loss": 0.5217205882072449, "train_batch_size": 32}, {"train_loss": 0.5186464786529541, "train_batch_size": 32}, {"train_loss": 0.3577916622161865, "train_batch_size": 32}, {"train_loss": 0.35599783062934875, "train_batch_size": 32}, {"train_loss": 0.2917173504829407, "train_batch_size": 32}, {"train_loss": 0.38975244760513306, "train_batch_size": 32}, {"train_loss": 0.28105998039245605, "train_batch_size": 32}, {"train_loss": 0.1030430868268013, "train_batch_size": 32}, {"train_loss": 0.22916942834854126, "train_batch_size": 32}, {"train_loss": 0.3804602324962616, "train_batch_size": 32}, {"train_loss": 0.14860311150550842, "train_batch_size": 32}, {"train_loss": 0.41951602697372437, "train_batch_size": 32}, {"train_loss": 0.32852259278297424, "train_batch_size": 32}, {"train_loss": 0.5594950914382935, "train_batch_size": 32}, {"train_loss": 0.27917784452438354, "train_batch_size": 32}, {"train_loss": 0.23029503226280212, "train_batch_size": 32}, {"train_loss": 0.2534351348876953, "train_batch_size": 32}, {"train_loss": 0.21754322946071625, "train_batch_size": 32}, {"train_loss": 0.2873859107494354, "train_batch_size": 32}, {"train_loss": 0.2650565505027771, "train_batch_size": 32}, {"train_loss": 0.32023417949676514, "train_batch_size": 32}, {"train_loss": 0.2850719094276428, "train_batch_size": 32}, {"train_loss": 0.30595213174819946, "train_batch_size": 32}, {"train_loss": 0.41412821412086487, "train_batch_size": 32}, {"train_loss": 0.420646071434021, "train_batch_size": 32}, {"train_loss": 0.15268217027187347, "train_batch_size": 32}, {"train_loss": 0.1199536919593811, "train_batch_size": 32}, {"train_loss": 0.35876962542533875, "train_batch_size": 32}, {"train_loss": 0.3651232123374939, "train_batch_size": 32}, {"train_loss": 0.127106174826622, "train_batch_size": 32}, {"train_loss": 0.26117390394210815, "train_batch_size": 32}, {"train_loss": 0.304062157869339, "train_batch_size": 32}, {"train_loss": 0.10911811143159866, "train_batch_size": 32}, {"train_loss": 0.13729165494441986, "train_batch_size": 32}, {"train_loss": 0.34154078364372253, "train_batch_size": 32}, {"train_loss": 0.5186271071434021, "train_batch_size": 32}, {"train_loss": 0.49108636379241943, "train_batch_size": 32}, {"train_loss": 0.30498838424682617, "train_batch_size": 32}, {"train_loss": 0.3114929795265198, "train_batch_size": 32}, {"train_loss": 0.37667882442474365, "train_batch_size": 32}, {"train_loss": 0.2316984385251999, "train_batch_size": 32}, {"train_loss": 0.20635345578193665, "train_batch_size": 32}, {"train_loss": 0.29625964164733887, "train_batch_size": 32}, {"train_loss": 0.33774614334106445, "train_batch_size": 32}, {"train_loss": 0.30786365270614624, "train_batch_size": 32}, {"train_loss": 0.24282430112361908, "train_batch_size": 32}, {"train_loss": 0.2851645350456238, "train_batch_size": 32}, {"train_loss": 0.5686015486717224, "train_batch_size": 32}, {"train_loss": 0.27907809615135193, "train_batch_size": 32}, {"train_loss": 0.44742992520332336, "train_batch_size": 32}, {"train_loss": 0.315703809261322, "train_batch_size": 32}, {"train_loss": 0.3110670745372772, "train_batch_size": 32}, {"train_loss": 0.2190447747707367, "train_batch_size": 32}, {"train_loss": 0.3124803304672241, "train_batch_size": 32}, {"train_loss": 0.38137784600257874, "train_batch_size": 32}, {"train_loss": 0.1773633062839508, "train_batch_size": 32}, {"train_loss": 0.19775469601154327, "train_batch_size": 32}, {"train_loss": 0.21548917889595032, "train_batch_size": 32}, {"train_loss": 0.2867174744606018, "train_batch_size": 32}, {"train_loss": 0.27042892575263977, "train_batch_size": 32}, {"train_loss": 0.19137635827064514, "train_batch_size": 32}, {"train_loss": 0.3215886652469635, "train_batch_size": 32}, {"train_loss": 0.5722286701202393, "train_batch_size": 32}, {"train_loss": 0.22697429358959198, "train_batch_size": 32}, {"train_loss": 0.31340593099594116, "train_batch_size": 32}, {"train_loss": 0.2288960963487625, "train_batch_size": 32}, {"train_loss": 0.26284247636795044, "train_batch_size": 32}, {"train_loss": 0.43966957926750183, "train_batch_size": 32}, {"train_loss": 0.3880924880504608, "train_batch_size": 32}, {"train_loss": 0.170981764793396, "train_batch_size": 32}, {"train_loss": 0.3378233015537262, "train_batch_size": 32}, {"train_loss": 0.17308129370212555, "train_batch_size": 32}, {"train_loss": 0.1795988380908966, "train_batch_size": 32}, {"train_loss": 0.33743077516555786, "train_batch_size": 32}, {"train_loss": 0.4489445686340332, "train_batch_size": 32}, {"train_loss": 0.26864659786224365, "train_batch_size": 32}, {"train_loss": 0.34816569089889526, "train_batch_size": 32}, {"train_loss": 0.33813387155532837, "train_batch_size": 32}, {"train_loss": 0.33288833498954773, "train_batch_size": 32}, {"train_loss": 0.2213437706232071, "train_batch_size": 32}, {"train_loss": 0.19326616823673248, "train_batch_size": 32}, {"train_loss": 0.2432273030281067, "train_batch_size": 32}, {"train_loss": 0.20620235800743103, "train_batch_size": 32}, {"train_loss": 0.14574986696243286, "train_batch_size": 32}, {"train_loss": 0.20332476496696472, "train_batch_size": 32}, {"train_loss": 0.04913082346320152, "train_batch_size": 32}, {"train_loss": 0.11283624172210693, "train_batch_size": 32}, {"train_loss": 0.24106745421886444, "train_batch_size": 32}, {"train_loss": 0.4523710608482361, "train_batch_size": 32}, {"train_loss": 0.23261626064777374, "train_batch_size": 32}, {"train_loss": 0.22747786343097687, "train_batch_size": 32}, {"train_loss": 0.32609421014785767, "train_batch_size": 32}, {"train_loss": 0.39808955788612366, "train_batch_size": 32}, {"train_loss": 0.1420709192752838, "train_batch_size": 32}, {"train_loss": 0.2319653034210205, "train_batch_size": 32}, {"train_loss": 0.08938279002904892, "train_batch_size": 32}, {"train_loss": 0.33410096168518066, "train_batch_size": 32}, {"train_loss": 0.3374094069004059, "train_batch_size": 32}, {"train_loss": 0.29809945821762085, "train_batch_size": 32}, {"train_loss": 0.4709413945674896, "train_batch_size": 32}, {"train_loss": 0.23459140956401825, "train_batch_size": 32}, {"train_loss": 0.22611938416957855, "train_batch_size": 32}, {"train_loss": 0.22089765965938568, "train_batch_size": 32}, {"train_loss": 0.24486954510211945, "train_batch_size": 32}, {"train_loss": 0.32689255475997925, "train_batch_size": 32}, {"train_loss": 0.38324373960494995, "train_batch_size": 32}, {"train_loss": 0.31531646847724915, "train_batch_size": 32}, {"train_loss": 0.2631927728652954, "train_batch_size": 32}, {"train_loss": 0.25030043721199036, "train_batch_size": 32}, {"train_loss": 0.4859209954738617, "train_batch_size": 32}, {"train_loss": 0.3949986696243286, "train_batch_size": 32}, {"train_loss": 0.38616836071014404, "train_batch_size": 32}, {"train_loss": 0.48638564348220825, "train_batch_size": 32}, {"train_loss": 0.2714959383010864, "train_batch_size": 32}, {"train_loss": 0.3875514268875122, "train_batch_size": 32}, {"train_loss": 0.16618523001670837, "train_batch_size": 32}, {"train_loss": 0.1715899407863617, "train_batch_size": 32}, {"train_loss": 0.1139771118760109, "train_batch_size": 32}, {"train_loss": 0.3193969130516052, "train_batch_size": 32}, {"train_loss": 0.4767724573612213, "train_batch_size": 32}, {"train_loss": 0.29608720541000366, "train_batch_size": 32}, {"train_loss": 0.43853241205215454, "train_batch_size": 32}, {"train_loss": 0.5132154822349548, "train_batch_size": 32}, {"train_loss": 0.2533140480518341, "train_batch_size": 32}, {"train_loss": 0.19915948808193207, "train_batch_size": 32}, {"train_loss": 0.16010457277297974, "train_batch_size": 32}, {"train_loss": 0.1990034580230713, "train_batch_size": 32}, {"train_loss": 0.2774202227592468, "train_batch_size": 32}, {"train_loss": 0.0539977103471756, "train_batch_size": 32}, {"train_loss": 0.19722121953964233, "train_batch_size": 32}, {"train_loss": 0.37370291352272034, "train_batch_size": 32}, {"train_loss": 0.2548092305660248, "train_batch_size": 32}, {"train_loss": 0.40612363815307617, "train_batch_size": 32}, {"train_loss": 0.3265266716480255, "train_batch_size": 32}, {"train_loss": 0.2692486345767975, "train_batch_size": 32}, {"train_loss": 0.08770450949668884, "train_batch_size": 32}, {"train_loss": 0.3132553696632385, "train_batch_size": 32}, {"train_loss": 0.5864998698234558, "train_batch_size": 32}, {"train_loss": 0.30510687828063965, "train_batch_size": 32}, {"train_loss": 0.2906157970428467, "train_batch_size": 32}, {"train_loss": 0.44182538986206055, "train_batch_size": 32}, {"train_loss": 0.2208428978919983, "train_batch_size": 32}, {"train_loss": 0.12643204629421234, "train_batch_size": 32}, {"train_loss": 0.23315827548503876, "train_batch_size": 32}, {"train_loss": 0.38985010981559753, "train_batch_size": 32}, {"train_loss": 0.2885671854019165, "train_batch_size": 32}, {"train_loss": 0.4585196077823639, "train_batch_size": 32}, {"train_loss": 0.26119494438171387, "train_batch_size": 32}, {"train_loss": 0.11000357568264008, "train_batch_size": 32}, {"train_loss": 0.38284042477607727, "train_batch_size": 32}, {"train_loss": 0.16033285856246948, "train_batch_size": 32}, {"train_loss": 0.15478076040744781, "train_batch_size": 32}, {"train_loss": 0.24685251712799072, "train_batch_size": 32}, {"train_loss": 0.20861607789993286, "train_batch_size": 32}, {"train_loss": 0.23305705189704895, "train_batch_size": 32}, {"train_loss": 0.1942673921585083, "train_batch_size": 32}, {"train_loss": 0.25191986560821533, "train_batch_size": 32}, {"train_loss": 0.34045839309692383, "train_batch_size": 32}, {"train_loss": 0.4513956606388092, "train_batch_size": 32}, {"train_loss": 0.24667474627494812, "train_batch_size": 32}, {"train_loss": 0.28753483295440674, "train_batch_size": 32}, {"train_loss": 0.4843803346157074, "train_batch_size": 32}, {"train_loss": 0.32873988151550293, "train_batch_size": 32}, {"train_loss": 0.23968590795993805, "train_batch_size": 32}, {"train_loss": 0.18690408766269684, "train_batch_size": 32}, {"train_loss": 0.10046301782131195, "train_batch_size": 32}, {"train_loss": 0.26044759154319763, "train_batch_size": 32}, {"train_loss": 0.42552435398101807, "train_batch_size": 32}, {"train_loss": 0.3340235948562622, "train_batch_size": 32}, {"train_loss": 0.431132435798645, "train_batch_size": 32}, {"train_loss": 0.16399572789669037, "train_batch_size": 32}, {"train_loss": 0.09990294277667999, "train_batch_size": 32}, {"train_loss": 0.33064407110214233, "train_batch_size": 32}, {"train_loss": 0.2031547725200653, "train_batch_size": 32}, {"train_loss": 0.3842003643512726, "train_batch_size": 32}, {"train_loss": 0.1723443865776062, "train_batch_size": 32}, {"train_loss": 0.3510899543762207, "train_batch_size": 32}, {"train_loss": 0.3064655363559723, "train_batch_size": 32}, {"train_loss": 0.37449705600738525, "train_batch_size": 32}, {"train_loss": 0.2668974995613098, "train_batch_size": 32}, {"train_loss": 0.12971994280815125, "train_batch_size": 32}, {"train_loss": 0.11546555161476135, "train_batch_size": 32}, {"train_loss": 0.16716313362121582, "train_batch_size": 32}, {"train_loss": 0.2471841722726822, "train_batch_size": 32}, {"train_loss": 0.3580653965473175, "train_batch_size": 32}, {"train_loss": 0.2768890857696533, "train_batch_size": 32}, {"train_loss": 0.31282734870910645, "train_batch_size": 32}, {"train_loss": 0.26549452543258667, "train_batch_size": 32}, {"train_loss": 0.3206198811531067, "train_batch_size": 32}, {"train_loss": 0.20902769267559052, "train_batch_size": 32}, {"train_loss": 0.14372918009757996, "train_batch_size": 32}, {"train_loss": 0.4182807505130768, "train_batch_size": 32}, {"train_loss": 0.16960939764976501, "train_batch_size": 32}, {"train_loss": 0.2223692387342453, "train_batch_size": 32}, {"train_loss": 0.33052024245262146, "train_batch_size": 32}, {"train_loss": 0.2023029923439026, "train_batch_size": 32}, {"train_loss": 0.22879904508590698, "train_batch_size": 32}, {"train_loss": 0.11262576282024384, "train_batch_size": 32}, {"train_loss": 0.4554392695426941, "train_batch_size": 32}, {"train_loss": 0.2407769411802292, "train_batch_size": 32}, {"train_loss": 0.10605349391698837, "train_batch_size": 32}, {"train_loss": 0.1616496443748474, "train_batch_size": 32}, {"train_loss": 0.16598919034004211, "train_batch_size": 32}, {"train_loss": 0.30963969230651855, "train_batch_size": 32}, {"train_loss": 0.3725680708885193, "train_batch_size": 32}, {"train_loss": 0.37042945623397827, "train_batch_size": 32}, {"train_loss": 0.30566322803497314, "train_batch_size": 32}, {"train_loss": 0.2784290313720703, "train_batch_size": 32}, {"train_loss": 0.23602639138698578, "train_batch_size": 32}, {"train_loss": 0.17527753114700317, "train_batch_size": 32}, {"train_loss": 0.2285432070493698, "train_batch_size": 32}, {"train_loss": 0.20970743894577026, "train_batch_size": 32}, {"train_loss": 0.292511522769928, "train_batch_size": 32}, {"train_loss": 0.4055117666721344, "train_batch_size": 32}, {"train_loss": 0.18976183235645294, "train_batch_size": 32}, {"train_loss": 0.3501943349838257, "train_batch_size": 32}, {"train_loss": 0.1528298407793045, "train_batch_size": 32}, {"train_loss": 0.10619786381721497, "train_batch_size": 32}, {"train_loss": 0.2904539406299591, "train_batch_size": 32}, {"train_loss": 0.21441370248794556, "train_batch_size": 32}, {"train_loss": 0.38732779026031494, "train_batch_size": 32}, {"train_loss": 0.45245057344436646, "train_batch_size": 32}, {"train_loss": 0.4182828664779663, "train_batch_size": 32}, {"train_loss": 0.3410816788673401, "train_batch_size": 32}, {"train_loss": 0.13614167273044586, "train_batch_size": 32}, {"train_loss": 0.4295027256011963, "train_batch_size": 32}, {"train_loss": 0.2816675305366516, "train_batch_size": 32}, {"train_loss": 0.21235428750514984, "train_batch_size": 32}, {"train_loss": 0.08453906327486038, "train_batch_size": 32}, {"train_loss": 0.507800817489624, "train_batch_size": 32}, {"train_loss": 0.23560255765914917, "train_batch_size": 32}, {"train_loss": 0.17540061473846436, "train_batch_size": 32}, {"train_loss": 0.39574307203292847, "train_batch_size": 32}, {"train_loss": 0.14169394969940186, "train_batch_size": 32}, {"train_loss": 0.20327505469322205, "train_batch_size": 32}, {"train_loss": 0.26965099573135376, "train_batch_size": 32}, {"train_loss": 0.26616567373275757, "train_batch_size": 32}, {"train_loss": 0.2353619635105133, "train_batch_size": 32}, {"train_loss": 0.19389167428016663, "train_batch_size": 32}, {"train_loss": 0.1833418309688568, "train_batch_size": 32}, {"train_loss": 0.3837679624557495, "train_batch_size": 32}, {"train_loss": 0.715846061706543, "train_batch_size": 32}, {"train_loss": 0.2638666331768036, "train_batch_size": 32}, {"train_loss": 0.2372889667749405, "train_batch_size": 32}, {"train_loss": 0.20624007284641266, "train_batch_size": 32}, {"train_loss": 0.44457435607910156, "train_batch_size": 32}, {"train_loss": 0.3958105444908142, "train_batch_size": 32}, {"train_loss": 0.3269980549812317, "train_batch_size": 32}, {"train_loss": 0.30513888597488403, "train_batch_size": 32}, {"train_loss": 0.2573840022087097, "train_batch_size": 32}, {"train_loss": 0.20262855291366577, "train_batch_size": 32}, {"train_loss": 0.23284727334976196, "train_batch_size": 32}, {"train_loss": 0.3335815966129303, "train_batch_size": 32}, {"train_loss": 0.4407174289226532, "train_batch_size": 32}, {"train_loss": 0.21545502543449402, "train_batch_size": 32}, {"train_loss": 0.2822709381580353, "train_batch_size": 32}, {"train_loss": 0.2515188753604889, "train_batch_size": 32}, {"train_loss": 0.21767182648181915, "train_batch_size": 32}, {"train_loss": 0.3431893289089203, "train_batch_size": 32}, {"train_loss": 0.24820542335510254, "train_batch_size": 32}, {"train_loss": 0.19016133248806, "train_batch_size": 32}, {"train_loss": 0.10225541889667511, "train_batch_size": 32}, {"train_loss": 0.4311639368534088, "train_batch_size": 32}, {"train_loss": 0.4267807602882385, "train_batch_size": 32}, {"train_loss": 0.28426897525787354, "train_batch_size": 32}, {"train_loss": 0.5281420350074768, "train_batch_size": 32}, {"train_loss": 0.1679157316684723, "train_batch_size": 32}, {"train_loss": 0.396175354719162, "train_batch_size": 32}, {"train_loss": 0.2603103220462799, "train_batch_size": 32}, {"train_loss": 0.2669481039047241, "train_batch_size": 32}, {"train_loss": 0.4669848680496216, "train_batch_size": 32}, {"train_loss": 0.3681790232658386, "train_batch_size": 32}, {"train_loss": 0.31298214197158813, "train_batch_size": 32}, {"train_loss": 0.49009039998054504, "train_batch_size": 32}, {"train_loss": 0.3699941039085388, "train_batch_size": 32}, {"train_loss": 0.35073983669281006, "train_batch_size": 32}, {"train_loss": 0.25830838084220886, "train_batch_size": 32}, {"train_loss": 0.49997034668922424, "train_batch_size": 32}, {"train_loss": 0.20671695470809937, "train_batch_size": 32}, {"train_loss": 0.36529460549354553, "train_batch_size": 32}, {"train_loss": 0.23244787752628326, "train_batch_size": 32}, {"train_loss": 0.27229076623916626, "train_batch_size": 32}, {"train_loss": 0.2959592342376709, "train_batch_size": 32}, {"train_loss": 0.3528136610984802, "train_batch_size": 32}, {"train_loss": 0.18295200169086456, "train_batch_size": 32}, {"train_loss": 0.20260395109653473, "train_batch_size": 32}, {"train_loss": 0.4365274906158447, "train_batch_size": 32}, {"train_loss": 0.21813714504241943, "train_batch_size": 32}, {"train_loss": 0.5086368918418884, "train_batch_size": 32}, {"train_loss": 0.3100345730781555, "train_batch_size": 32}, {"train_loss": 0.3679165840148926, "train_batch_size": 32}, {"train_loss": 0.43403851985931396, "train_batch_size": 32}, {"train_loss": 0.208927184343338, "train_batch_size": 32}, {"train_loss": 0.4063294529914856, "train_batch_size": 32}, {"train_loss": 0.4513184428215027, "train_batch_size": 32}, {"train_loss": 0.26627328991889954, "train_batch_size": 32}, {"train_loss": 0.21440914273262024, "train_batch_size": 32}, {"train_loss": 0.31044286489486694, "train_batch_size": 32}, {"train_loss": 0.2255464494228363, "train_batch_size": 32}, {"train_loss": 0.3249604105949402, "train_batch_size": 32}, {"train_loss": 0.34160542488098145, "train_batch_size": 32}, {"train_loss": 0.4397035241127014, "train_batch_size": 32}, {"train_loss": 0.27265673875808716, "train_batch_size": 32}, {"train_loss": 0.21650494635105133, "train_batch_size": 32}, {"train_loss": 0.5211851596832275, "train_batch_size": 32}, {"train_loss": 0.20954468846321106, "train_batch_size": 32}, {"train_loss": 0.2123364955186844, "train_batch_size": 32}, {"train_loss": 0.12025515735149384, "train_batch_size": 32}, {"train_loss": 0.36334800720214844, "train_batch_size": 32}, {"train_loss": 0.37313514947891235, "train_batch_size": 32}, {"train_loss": 0.20570507645606995, "train_batch_size": 32}, {"train_loss": 0.2918638586997986, "train_batch_size": 32}, {"train_loss": 0.46029549837112427, "train_batch_size": 32}, {"train_loss": 0.2600899338722229, "train_batch_size": 32}, {"train_loss": 0.223676860332489, "train_batch_size": 32}, {"train_loss": 0.12237843871116638, "train_batch_size": 32}, {"train_loss": 0.40569138526916504, "train_batch_size": 32}, {"train_loss": 0.35796406865119934, "train_batch_size": 32}, {"train_loss": 0.18442127108573914, "train_batch_size": 32}, {"train_loss": 0.38314706087112427, "train_batch_size": 32}, {"train_loss": 0.4018908143043518, "train_batch_size": 32}, {"train_loss": 0.5135220885276794, "train_batch_size": 32}, {"train_loss": 0.2882845401763916, "train_batch_size": 32}, {"train_loss": 0.1832101047039032, "train_batch_size": 32}, {"train_loss": 0.23063284158706665, "train_batch_size": 32}, {"train_loss": 0.4802728593349457, "train_batch_size": 32}, {"train_loss": 0.29534631967544556, "train_batch_size": 32}, {"train_loss": 0.204806387424469, "train_batch_size": 32}, {"train_loss": 0.23819740116596222, "train_batch_size": 32}, {"train_loss": 0.16660478711128235, "train_batch_size": 32}, {"train_loss": 0.5635669827461243, "train_batch_size": 32}, {"train_loss": 0.35147154331207275, "train_batch_size": 32}, {"train_loss": 0.11111634969711304, "train_batch_size": 32}, {"train_loss": 0.31269729137420654, "train_batch_size": 32}, {"train_loss": 0.2448590099811554, "train_batch_size": 32}, {"train_loss": 0.23985905945301056, "train_batch_size": 32}, {"train_loss": 0.4201602041721344, "train_batch_size": 32}, {"train_loss": 0.22887282073497772, "train_batch_size": 32}, {"train_loss": 0.27724260091781616, "train_batch_size": 32}, {"train_loss": 0.325962632894516, "train_batch_size": 32}, {"train_loss": 0.2100294977426529, "train_batch_size": 32}, {"train_loss": 0.474725604057312, "train_batch_size": 32}, {"train_loss": 0.30238649249076843, "train_batch_size": 32}, {"train_loss": 0.19831624627113342, "train_batch_size": 32}, {"train_loss": 0.188666433095932, "train_batch_size": 32}, {"train_loss": 0.35055285692214966, "train_batch_size": 32}, {"train_loss": 0.3716975450515747, "train_batch_size": 32}, {"train_loss": 0.1369980126619339, "train_batch_size": 32}, {"train_loss": 0.3474874496459961, "train_batch_size": 32}, {"train_loss": 0.29462239146232605, "train_batch_size": 32}, {"train_loss": 0.5585892200469971, "train_batch_size": 32}, {"train_loss": 0.35136184096336365, "train_batch_size": 32}, {"train_loss": 0.23612293601036072, "train_batch_size": 32}, {"train_loss": 0.19209372997283936, "train_batch_size": 32}, {"train_loss": 0.3604148328304291, "train_batch_size": 32}, {"train_loss": 0.25849127769470215, "train_batch_size": 32}, {"train_loss": 0.19070616364479065, "train_batch_size": 32}, {"train_loss": 0.2867743968963623, "train_batch_size": 32}, {"train_loss": 0.32695087790489197, "train_batch_size": 32}, {"train_loss": 0.1752486526966095, "train_batch_size": 32}, {"train_loss": 0.21722351014614105, "train_batch_size": 32}, {"train_loss": 0.39978936314582825, "train_batch_size": 32}, {"train_loss": 0.2650814950466156, "train_batch_size": 32}, {"train_loss": 0.27740341424942017, "train_batch_size": 32}, {"train_loss": 0.2900666296482086, "train_batch_size": 32}, {"train_loss": 0.2825438380241394, "train_batch_size": 32}, {"train_loss": 0.243772491812706, "train_batch_size": 32}, {"train_loss": 0.3960210978984833, "train_batch_size": 32}, {"train_loss": 0.12119849771261215, "train_batch_size": 32}, {"train_loss": 0.3279247283935547, "train_batch_size": 32}, {"train_loss": 0.12774358689785004, "train_batch_size": 32}, {"train_loss": 0.4295639991760254, "train_batch_size": 32}, {"train_loss": 0.43210774660110474, "train_batch_size": 32}, {"train_loss": 0.34933996200561523, "train_batch_size": 32}, {"train_loss": 0.2711816430091858, "train_batch_size": 32}, {"train_loss": 0.16604238748550415, "train_batch_size": 32}, {"train_loss": 0.30419743061065674, "train_batch_size": 32}, {"train_loss": 0.21047811210155487, "train_batch_size": 32}, {"train_loss": 0.2572581171989441, "train_batch_size": 32}, {"train_loss": 0.34501147270202637, "train_batch_size": 32}, {"train_loss": 0.3358256220817566, "train_batch_size": 32}, {"train_loss": 0.3014928102493286, "train_batch_size": 32}, {"train_loss": 0.25900641083717346, "train_batch_size": 32}, {"train_loss": 0.2746679186820984, "train_batch_size": 32}, {"train_loss": 0.21451719105243683, "train_batch_size": 32}, {"train_loss": 0.26060599088668823, "train_batch_size": 32}, {"train_loss": 0.24882327020168304, "train_batch_size": 32}, {"train_loss": 0.4492570161819458, "train_batch_size": 32}, {"train_loss": 0.10847070813179016, "train_batch_size": 32}, {"train_loss": 0.39273637533187866, "train_batch_size": 32}, {"train_loss": 0.314261257648468, "train_batch_size": 32}, {"train_loss": 0.3480561375617981, "train_batch_size": 32}, {"train_loss": 0.33980414271354675, "train_batch_size": 32}, {"train_loss": 0.17022031545639038, "train_batch_size": 32}, {"train_loss": 0.38920313119888306, "train_batch_size": 32}, {"train_loss": 0.30643847584724426, "train_batch_size": 32}, {"train_loss": 0.5418075323104858, "train_batch_size": 32}, {"train_loss": 0.3920939862728119, "train_batch_size": 32}, {"train_loss": 0.34570151567459106, "train_batch_size": 32}, {"train_loss": 0.3480556309223175, "train_batch_size": 32}, {"train_loss": 0.1858920454978943, "train_batch_size": 32}, {"train_loss": 0.30545276403427124, "train_batch_size": 32}, {"train_loss": 0.13138893246650696, "train_batch_size": 32}, {"train_loss": 0.21675512194633484, "train_batch_size": 32}, {"train_loss": 0.40149393677711487, "train_batch_size": 32}, {"train_loss": 0.3646427094936371, "train_batch_size": 32}, {"train_loss": 0.3884613513946533, "train_batch_size": 32}, {"train_loss": 0.2745104432106018, "train_batch_size": 32}, {"train_loss": 0.21752625703811646, "train_batch_size": 32}, {"train_loss": 0.15253077447414398, "train_batch_size": 32}, {"train_loss": 0.28326916694641113, "train_batch_size": 32}, {"train_loss": 0.20307771861553192, "train_batch_size": 32}, {"train_loss": 0.1929289549589157, "train_batch_size": 32}, {"train_loss": 0.4035918116569519, "train_batch_size": 32}, {"train_loss": 0.28717339038848877, "train_batch_size": 32}, {"train_loss": 0.3847084641456604, "train_batch_size": 32}, {"train_loss": 0.15749645233154297, "train_batch_size": 32}, {"train_loss": 0.4614516496658325, "train_batch_size": 32}, {"train_loss": 0.33829909563064575, "train_batch_size": 32}, {"train_loss": 0.5918338298797607, "train_batch_size": 32}, {"train_loss": 0.13711661100387573, "train_batch_size": 32}, {"train_loss": 0.3101113438606262, "train_batch_size": 32}, {"train_loss": 0.16312871873378754, "train_batch_size": 32}, {"train_loss": 0.5215229988098145, "train_batch_size": 32}, {"train_loss": 0.2552194595336914, "train_batch_size": 32}, {"train_loss": 0.42702409625053406, "train_batch_size": 32}, {"train_loss": 0.2125350534915924, "train_batch_size": 32}, {"train_loss": 0.3581598103046417, "train_batch_size": 32}, {"train_loss": 0.27728474140167236, "train_batch_size": 32}, {"train_loss": 0.35408517718315125, "train_batch_size": 32}, {"train_loss": 0.3600800633430481, "train_batch_size": 32}, {"train_loss": 0.44428589940071106, "train_batch_size": 32}, {"train_loss": 0.16311347484588623, "train_batch_size": 32}, {"train_loss": 0.3284854590892792, "train_batch_size": 32}, {"train_loss": 0.34175199270248413, "train_batch_size": 32}, {"train_loss": 0.21642039716243744, "train_batch_size": 32}, {"train_loss": 0.340902179479599, "train_batch_size": 32}, {"train_loss": 0.28700900077819824, "train_batch_size": 32}, {"train_loss": 0.31656378507614136, "train_batch_size": 32}, {"train_loss": 0.2764437794685364, "train_batch_size": 32}, {"train_loss": 0.28234240412712097, "train_batch_size": 32}, {"train_loss": 0.28470659255981445, "train_batch_size": 32}, {"train_loss": 0.24558384716510773, "train_batch_size": 32}, {"train_loss": 0.26247918605804443, "train_batch_size": 32}, {"train_loss": 0.17267285287380219, "train_batch_size": 32}, {"train_loss": 0.3399728536605835, "train_batch_size": 32}, {"train_loss": 0.25620436668395996, "train_batch_size": 32}, {"train_loss": 0.3318216800689697, "train_batch_size": 32}, {"train_loss": 0.1794097125530243, "train_batch_size": 32}, {"train_loss": 0.586367666721344, "train_batch_size": 32}, {"train_loss": 0.17410407960414886, "train_batch_size": 32}, {"train_loss": 0.23758617043495178, "train_batch_size": 32}, {"train_loss": 0.45430493354797363, "train_batch_size": 32}, {"train_loss": 0.6065315008163452, "train_batch_size": 32}, {"train_loss": 0.1641882210969925, "train_batch_size": 32}, {"train_loss": 0.18455947935581207, "train_batch_size": 32}, {"train_loss": 0.2289648950099945, "train_batch_size": 32}, {"train_loss": 0.14730176329612732, "train_batch_size": 32}, {"train_loss": 0.3298914432525635, "train_batch_size": 32}, {"train_loss": 0.3185132145881653, "train_batch_size": 32}, {"train_loss": 0.21105296909809113, "train_batch_size": 32}, {"train_loss": 0.47070178389549255, "train_batch_size": 32}, {"train_loss": 0.16224658489227295, "train_batch_size": 32}, {"train_loss": 0.2602447271347046, "train_batch_size": 32}, {"train_loss": 0.43985670804977417, "train_batch_size": 32}, {"train_loss": 0.19622951745986938, "train_batch_size": 32}, {"train_loss": 0.4293724596500397, "train_batch_size": 32}, {"train_loss": 0.26661500334739685, "train_batch_size": 32}, {"train_loss": 0.24808856844902039, "train_batch_size": 32}, {"train_loss": 0.5102986693382263, "train_batch_size": 32}, {"train_loss": 0.21578313410282135, "train_batch_size": 32}, {"train_loss": 0.32732704281806946, "train_batch_size": 32}, {"train_loss": 0.3878266215324402, "train_batch_size": 32}, {"train_loss": 0.26894986629486084, "train_batch_size": 32}, {"train_loss": 0.3865443468093872, "train_batch_size": 32}, {"train_loss": 0.1786687672138214, "train_batch_size": 32}, {"train_loss": 0.16000226140022278, "train_batch_size": 32}, {"train_loss": 0.22109907865524292, "train_batch_size": 32}, {"train_loss": 0.36618536710739136, "train_batch_size": 32}, {"train_loss": 0.4005263149738312, "train_batch_size": 32}, {"train_loss": 0.1959080994129181, "train_batch_size": 32}, {"train_loss": 0.29269853234291077, "train_batch_size": 32}, {"train_loss": 0.36788180470466614, "train_batch_size": 32}, {"train_loss": 0.16268303990364075, "train_batch_size": 32}, {"train_loss": 0.1564057171344757, "train_batch_size": 32}, {"train_loss": 0.4491569995880127, "train_batch_size": 32}, {"train_loss": 0.6089285612106323, "train_batch_size": 32}, {"train_loss": 0.42150643467903137, "train_batch_size": 32}, {"train_loss": 0.23766428232192993, "train_batch_size": 32}, {"train_loss": 0.2572590708732605, "train_batch_size": 32}, {"train_loss": 0.4699241518974304, "train_batch_size": 32}, {"train_loss": 0.3210870921611786, "train_batch_size": 32}, {"train_loss": 0.10278704762458801, "train_batch_size": 32}, {"train_loss": 0.16620151698589325, "train_batch_size": 32}, {"train_loss": 0.10566802322864532, "train_batch_size": 32}, {"train_loss": 0.20896494388580322, "train_batch_size": 32}, {"train_loss": 0.1652378886938095, "train_batch_size": 32}, {"train_loss": 0.2429603785276413, "train_batch_size": 32}, {"train_loss": 0.1739622801542282, "train_batch_size": 32}, {"train_loss": 0.20514488220214844, "train_batch_size": 32}, {"train_loss": 0.289171040058136, "train_batch_size": 32}, {"train_loss": 0.2428799271583557, "train_batch_size": 32}, {"train_loss": 0.15290845930576324, "train_batch_size": 32}, {"train_loss": 0.3384023904800415, "train_batch_size": 32}, {"train_loss": 0.4879244267940521, "train_batch_size": 32}, {"train_loss": 0.2710493206977844, "train_batch_size": 32}, {"train_loss": 0.1006886214017868, "train_batch_size": 32}, {"train_loss": 0.20695310831069946, "train_batch_size": 32}, {"train_loss": 0.33458396792411804, "train_batch_size": 28}, {"valid_loss": 0.278732031583786, "valid_batch_size": 32}, {"valid_loss": 0.2676278352737427, "valid_batch_size": 32}, {"valid_loss": 0.2722240388393402, "valid_batch_size": 32}, {"valid_loss": 0.2792587876319885, "valid_batch_size": 32}, {"valid_loss": 0.30099982023239136, "valid_batch_size": 32}, {"valid_loss": 0.3810076117515564, "valid_batch_size": 32}, {"valid_loss": 0.30134332180023193, "valid_batch_size": 32}, {"valid_loss": 0.3193233609199524, "valid_batch_size": 32}, {"valid_loss": 0.2941541075706482, "valid_batch_size": 32}, {"valid_loss": 0.24733832478523254, "valid_batch_size": 32}, {"valid_loss": 0.37529227137565613, "valid_batch_size": 32}, {"valid_loss": 0.5056485533714294, "valid_batch_size": 32}, {"valid_loss": 0.3028712868690491, "valid_batch_size": 32}, {"valid_loss": 0.10183289647102356, "valid_batch_size": 32}, {"valid_loss": 0.517633318901062, "valid_batch_size": 32}, {"valid_loss": 0.31544703245162964, "valid_batch_size": 32}, {"valid_loss": 0.4308801591396332, "valid_batch_size": 32}, {"valid_loss": 0.3271762728691101, "valid_batch_size": 32}, {"valid_loss": 0.14649391174316406, "valid_batch_size": 32}, {"valid_loss": 0.16865670680999756, "valid_batch_size": 32}, {"valid_loss": 0.2020239681005478, "valid_batch_size": 32}, {"valid_loss": 0.3156640827655792, "valid_batch_size": 32}, {"valid_loss": 0.33115845918655396, "valid_batch_size": 32}, {"valid_loss": 0.21114730834960938, "valid_batch_size": 32}, {"valid_loss": 0.14830495417118073, "valid_batch_size": 32}, {"valid_loss": 0.12378261983394623, "valid_batch_size": 32}, {"valid_loss": 0.37992626428604126, "valid_batch_size": 32}, {"valid_loss": 0.3412410020828247, "valid_batch_size": 32}, {"valid_loss": 0.2895711362361908, "valid_batch_size": 32}, {"valid_loss": 0.20925548672676086, "valid_batch_size": 32}, {"valid_loss": 0.4003465175628662, "valid_batch_size": 32}, {"valid_loss": 0.14516346156597137, "valid_batch_size": 32}, {"valid_loss": 0.2456112951040268, "valid_batch_size": 32}, {"valid_loss": 0.17383518815040588, "valid_batch_size": 32}, {"valid_loss": 0.32796210050582886, "valid_batch_size": 32}, {"valid_loss": 0.1320505142211914, "valid_batch_size": 32}, {"valid_loss": 0.6303578615188599, "valid_batch_size": 32}, {"valid_loss": 0.4323916435241699, "valid_batch_size": 32}, {"valid_loss": 0.08509299159049988, "valid_batch_size": 32}, {"valid_loss": 0.1786169558763504, "valid_batch_size": 32}, {"valid_loss": 0.08391806483268738, "valid_batch_size": 32}, {"valid_loss": 0.2136092483997345, "valid_batch_size": 32}, {"valid_loss": 0.3267592787742615, "valid_batch_size": 32}, {"valid_loss": 0.316799134016037, "valid_batch_size": 32}, {"valid_loss": 0.1708829700946808, "valid_batch_size": 32}, {"valid_loss": 0.23563924431800842, "valid_batch_size": 32}, {"valid_loss": 0.4805346131324768, "valid_batch_size": 32}, {"valid_loss": 0.34359902143478394, "valid_batch_size": 32}, {"valid_loss": 0.32152748107910156, "valid_batch_size": 32}, {"valid_loss": 0.3459455072879791, "valid_batch_size": 32}, {"valid_loss": 0.26799774169921875, "valid_batch_size": 32}, {"valid_loss": 0.2359538972377777, "valid_batch_size": 32}, {"valid_loss": 0.274828165769577, "valid_batch_size": 32}, {"valid_loss": 0.210114985704422, "valid_batch_size": 32}, {"valid_loss": 0.20866769552230835, "valid_batch_size": 32}, {"valid_loss": 0.2939907908439636, "valid_batch_size": 32}, {"valid_loss": 0.2019965946674347, "valid_batch_size": 32}, {"valid_loss": 0.399446964263916, "valid_batch_size": 32}, {"valid_loss": 0.396247923374176, "valid_batch_size": 32}, {"valid_loss": 0.20772218704223633, "valid_batch_size": 32}, {"valid_loss": 0.2403564304113388, "valid_batch_size": 32}, {"valid_loss": 0.3457130789756775, "valid_batch_size": 32}, {"valid_loss": 0.2389897108078003, "valid_batch_size": 32}, {"valid_loss": 0.3102274537086487, "valid_batch_size": 32}, {"valid_loss": 0.14102914929389954, "valid_batch_size": 32}, {"valid_loss": 0.3301771879196167, "valid_batch_size": 32}, {"valid_loss": 0.43045783042907715, "valid_batch_size": 32}, {"valid_loss": 0.24774278700351715, "valid_batch_size": 32}, {"valid_loss": 0.26975032687187195, "valid_batch_size": 32}, {"valid_loss": 0.15482355654239655, "valid_batch_size": 32}, {"valid_loss": 0.13294968008995056, "valid_batch_size": 32}, {"valid_loss": 0.40597254037857056, "valid_batch_size": 32}, {"valid_loss": 0.16487374901771545, "valid_batch_size": 32}, {"valid_loss": 0.2102847546339035, "valid_batch_size": 32}, {"valid_loss": 0.137233167886734, "valid_batch_size": 32}, {"valid_loss": 0.1539919674396515, "valid_batch_size": 32}, {"valid_loss": 0.5170003175735474, "valid_batch_size": 32}, {"valid_loss": 0.5102231502532959, "valid_batch_size": 32}, {"valid_loss": 0.20684963464736938, "valid_batch_size": 32}, {"valid_loss": 0.25871431827545166, "valid_batch_size": 32}, {"valid_loss": 0.23702016472816467, "valid_batch_size": 32}, {"valid_loss": 0.45510855317115784, "valid_batch_size": 32}, {"valid_loss": 0.14748334884643555, "valid_batch_size": 32}, {"valid_loss": 0.3333227336406708, "valid_batch_size": 32}, {"valid_loss": 0.351296603679657, "valid_batch_size": 32}, {"valid_loss": 0.34851130843162537, "valid_batch_size": 32}, {"valid_loss": 0.4042068123817444, "valid_batch_size": 32}, {"valid_loss": 0.1746182143688202, "valid_batch_size": 32}, {"valid_loss": 0.10482726246118546, "valid_batch_size": 32}, {"valid_loss": 0.36357736587524414, "valid_batch_size": 32}, {"valid_loss": 0.362383097410202, "valid_batch_size": 32}, {"valid_loss": 0.6810848116874695, "valid_batch_size": 32}, {"valid_loss": 0.371648907661438, "valid_batch_size": 32}, {"valid_loss": 0.07618837058544159, "valid_batch_size": 32}, {"valid_loss": 0.20050710439682007, "valid_batch_size": 32}, {"valid_loss": 0.27201542258262634, "valid_batch_size": 32}, {"valid_loss": 0.41193467378616333, "valid_batch_size": 32}, {"valid_loss": 0.5656229257583618, "valid_batch_size": 32}, {"valid_loss": 0.1707160472869873, "valid_batch_size": 32}, {"valid_loss": 0.2539620101451874, "valid_batch_size": 32}, {"valid_loss": 0.4967331886291504, "valid_batch_size": 32}, {"valid_loss": 0.30568045377731323, "valid_batch_size": 32}, {"valid_loss": 0.25533872842788696, "valid_batch_size": 32}, {"valid_loss": 0.18170669674873352, "valid_batch_size": 32}, {"valid_loss": 0.18679672479629517, "valid_batch_size": 32}, {"valid_loss": 0.20327863097190857, "valid_batch_size": 32}, {"valid_loss": 0.3408868610858917, "valid_batch_size": 32}, {"valid_loss": 0.35086512565612793, "valid_batch_size": 32}, {"valid_loss": 0.2577229142189026, "valid_batch_size": 32}, {"valid_loss": 0.3229132890701294, "valid_batch_size": 32}, {"valid_loss": 0.28444236516952515, "valid_batch_size": 32}, {"valid_loss": 0.5668821930885315, "valid_batch_size": 32}, {"valid_loss": 0.09629309922456741, "valid_batch_size": 32}, {"valid_loss": 0.33029186725616455, "valid_batch_size": 32}, {"valid_loss": 0.3131478428840637, "valid_batch_size": 32}, {"valid_loss": 0.21103215217590332, "valid_batch_size": 32}, {"valid_loss": 0.19468659162521362, "valid_batch_size": 32}, {"valid_loss": 0.22171105444431305, "valid_batch_size": 32}, {"valid_loss": 0.3110250234603882, "valid_batch_size": 32}, {"valid_loss": 0.20245549082756042, "valid_batch_size": 32}, {"valid_loss": 0.14452601969242096, "valid_batch_size": 32}, {"valid_loss": 0.4428887963294983, "valid_batch_size": 32}, {"valid_loss": 0.1567080020904541, "valid_batch_size": 32}, {"valid_loss": 0.1062716394662857, "valid_batch_size": 32}, {"valid_loss": 0.2286938577890396, "valid_batch_size": 32}, {"valid_loss": 0.14447060227394104, "valid_batch_size": 32}, {"valid_loss": 0.123304083943367, "valid_batch_size": 32}, {"valid_loss": 0.23717893660068512, "valid_batch_size": 32}, {"valid_loss": 0.336411714553833, "valid_batch_size": 32}, {"valid_loss": 0.5125373601913452, "valid_batch_size": 32}, {"valid_loss": 0.2942189574241638, "valid_batch_size": 32}, {"valid_loss": 0.1729060411453247, "valid_batch_size": 32}, {"valid_loss": 0.38847023248672485, "valid_batch_size": 32}, {"valid_loss": 0.2104419469833374, "valid_batch_size": 32}, {"valid_loss": 0.18078666925430298, "valid_batch_size": 32}, {"valid_loss": 0.23876889050006866, "valid_batch_size": 32}, {"valid_loss": 0.1417541801929474, "valid_batch_size": 32}, {"valid_loss": 0.36836785078048706, "valid_batch_size": 32}, {"valid_loss": 0.3849363625049591, "valid_batch_size": 32}, {"valid_loss": 0.5150489807128906, "valid_batch_size": 32}, {"valid_loss": 0.20662152767181396, "valid_batch_size": 32}, {"valid_loss": 0.2091166377067566, "valid_batch_size": 32}, {"valid_loss": 0.6622054576873779, "valid_batch_size": 32}, {"valid_loss": 0.30469197034835815, "valid_batch_size": 32}, {"valid_loss": 0.4672122001647949, "valid_batch_size": 32}, {"valid_loss": 0.15684333443641663, "valid_batch_size": 32}, {"valid_loss": 0.18062885105609894, "valid_batch_size": 32}, {"valid_loss": 0.11563500016927719, "valid_batch_size": 32}, {"valid_loss": 0.2757667899131775, "valid_batch_size": 32}, {"valid_loss": 0.1515556126832962, "valid_batch_size": 32}, {"valid_loss": 0.5627986788749695, "valid_batch_size": 32}, {"valid_loss": 0.1670532524585724, "valid_batch_size": 32}, {"valid_loss": 0.4083910286426544, "valid_batch_size": 32}, {"valid_loss": 0.13342881202697754, "valid_batch_size": 32}, {"valid_loss": 0.06613829731941223, "valid_batch_size": 32}, {"valid_loss": 0.17649081349372864, "valid_batch_size": 32}, {"valid_loss": 0.07901611179113388, "valid_batch_size": 8}], "epoch": 1, "train_batch_count": 1131, "valid_batch_count": 157, "dur": 2.961611270904541, "train_loss": 0.30343417480556667, "train_loss_best": true, "valid_loss": 0.2809211981654167, "valid_loss_best": true, "valid_acc": 0.9008, "valid_acc_best": true, "event_cp": true}]